MANIFEST.in
README
setup.cfg
setup.py
hexconnector/__init__.py
hexconnector/connector.py
hexconnector/version.py
hexconnector.egg-info/PKG-INFO
hexconnector.egg-info/SOURCES.txt
hexconnector.egg-info/dependency_links.txt
hexconnector.egg-info/not-zip-safe
hexconnector.egg-info/top_level.txt