Metadata-Version: 1.1
Name: hexconnector
Version: 0.1.1
Summary: Python Hexagonal Architecture with Dynamic Module Loading
Home-page: https://github.com/laco/python-hexconnector/
Author: László Andrási
Author-email: mail@laszloandrasi.com
License: BSD
Download-URL: https://github.com/laco/python-hexconnector/tarball/0.1.1
Platform: any
Classifier: Development Status :: 4 - Beta
Classifier: Environment :: Web Environment
Classifier: Intended Audience :: Developers
Classifier: License :: OSI Approved :: BSD License
Classifier: Operating System :: OS Independent
Classifier: Programming Language :: Python
Classifier: Programming Language :: Python :: 3
Classifier: Topic :: Software Development :: Libraries :: Python Modules
